snore/__init__.py
snore/snore.py
snore/utils.py
snore_embedding-0.3.3.dist-info/LICENSE
snore_embedding-0.3.3.dist-info/METADATA
snore_embedding-0.3.3.dist-info/WHEEL
snore_embedding-0.3.3.dist-info/top_level.txt
snore_embedding-0.3.3.dist-info/RECORD
